ioi_swarm/__init__.py
ioi_swarm/agent.py
ioi_swarm/client.py
ioi_swarm/ghost.py
ioi_swarm/tools.py
ioi_swarm/types.py
ioi_swarm/proto/__init__.py
ioi_swarm/proto/blockchain_pb2.py
ioi_swarm/proto/blockchain_pb2_grpc.py
ioi_swarm/proto/public_pb2.py
ioi_swarm/proto/public_pb2_grpc.py
ioi_swarm-0.1.2.dist-info/METADATA
ioi_swarm-0.1.2.dist-info/WHEEL
ioi_swarm-0.1.2.dist-info/RECORD
